{"(wait)":"(wait).gif","danBilly":"danBilly.png","danCreep":"danCreep.png",":hungry:":"{col}hungry{col}.png","lomSleep":"lomSleep.png","(punch)":"(punch).gif","danRE":"danRE.png","probsThis":"probsThis.png","(idea)":"(idea).gif","danHuh":"danHuh.png","(swear)":"(swear).gif","(facepalm)":"(facepalm).gif","danDead":"danDead.png","(sleep)":"(sleep).gif","trumpTrump":"trumpTrump.png","(pi)":"(pi).gif","probsSing":"probsSing.png",":amane:":"{col}amane{col}.png","eloiseWb":"eloiseWb.png","danRage":"danRage.png","danSexy":"danSexy.png","(bomb)":"(bomb).gif","lirikFEELS":"lirikFEELS.png","danGasp":"danGasp.png","eloiseMan":"eloiseMan.png","(angry)":"(angry).gif","danRekt":"danRekt.png","(whew)":"(whew).gif","danCringe":"danCringe.png","danGrump":"danGrump.png","danKnife":"danKnife.png","lirikGREAT":"lirikGREAT.png","laceDemon":"laceDemon.png","(think)":"(think).gif","(bow)":"(bow).gif","ohnSnake":"ohnSnake.png","danEZ":"danEZ.png","\\o\/":"{bsl}o{fsl}.gif","(talk)":"(talk).gif","ohnOcelot":"ohnOcelot.png","danCop":"danCop.png","(brb)":"(brb).gif","demanFlame":"demanFlame.png","(ninja)":"(ninja).gif","danBoy":"danBoy.png","danHate":"danHate.png","lomLurk":"lomLurk.png","laceSalt":"laceSalt.png","monkaGun":"monkaGun.png","nrageZzz":"nrageZzz.png","danDrive":"danDrive.png","GoldVo":"GoldVo.png","chippyThirst":"chippyThirst.png",":^)":"{col}^).gif","danCash":"danCash.png","lomLink":"lomLink.png","in4Doit":"in4Doit.png","(drunk)":"(drunk).gif","lirikNOT":"lirikNOT.png","koopaNuke":"koopaNuke.png","(party)":"(party).gif","lomSrs":"lomSrs.png","danLUL":"danLUL.png","trump0":"trump0.png","danDapper":"danDapper.png","lirikWc":"lirikWc.png",":steammocking:":"{col}steammocking{col}.png","(devil)":"(devil).gif","eloiseBan":"eloiseBan.png","lomSad":"lomSad.png",":steamhappy:":"{col}steamhappy{col}.png","danSad":"danSad.png",":steamfacepalm:":"{col}steamfacepalm{col}.png",":smokeybear:":"{col}smokeybear{col}.png",":S":"{col}S.gif","(nod)":"(nod).gif","coco":"coco.png",":kotori:":"{col}kotori{col}.png","(happy)":"(happy).gif","danHug":"danHug.png","(t)":"(t).gif",":3":"{col}3.gif","Volcania":"Volcania.png","trumpGive":"trumpGive.png","sodaCash":"sodaCash.png","RPGSword":"RPGSword.png","danSleep":"danSleep.png","RPGFlag":"RPGFlag.png","OMGScoots":"OMGScoots.png","(fry)":"(fry).png","(stop)":"(stop).gif","ohnSad":"ohnSad.png","eloiseLUL":"eloiseLUL.png","ohnNaked":"ohnNaked.png","necShip":"necShip.png","(bike)":"(bike).gif","LUL":"LUL.png","danWave":"danWave.png","dan1st":"dan1st.png","danHype":"danHype.png","lomThun":"lomThun.png","lomThink":"lomThink.png","lomSaron":"lomSaron.png","lomNot":"lomNot.png","gsamSpitfire":"gsamSpitfire.png","lomLUL":"lomLUL.png","lomGrill":"lomGrill.png","lomGasp":"lomGasp.png","lomBoo":"lomBoo.png","lomBeast":"lomBeast.png","danLewd":"danLewd.png","lomArmy":"lomArmy.png","danWait":"danWait.png","lomThwomp":"lomThwomp.png",":steamsad:":"{col}steamsad{col}.png","danIme":"danIme.png","(manny)":"(manny).png","(envy)":"(envy).gif","lirikTRUCK":"lirikTRUCK.png","danBlind":"danBlind.png","lirikFAKE":"lirikFAKE.png","lirikLEAN":"lirikLEAN.png","(shake)":"(shake).gif","danWE":"danWE.png","danFat":"danFat.png","(clock)":"(clock).gif","(yn)":"(yn).gif","(fubar)":"(fubar).gif","danYes":"danYes.png","eloiseNEET":"eloiseNEET.png","danLove":"danLove.png","(yawn)":"(yawn).gif","danCreeper":"danCreeper.png","legendaryCash":"legendaryCash.png","(cake)":"(cake).gif","(nerd)":"(nerd).gif","lacePuff":"lacePuff.png","laceHello":"laceHello.png","RPGHammer":"RPGHammer.png","kodoDvaCrazy":"kodoDvaCrazy.png","(tmi)":"(tmi).gif","lomYrel":"lomYrel.png","danNerd":"danNerd.png","lirikRIP":"lirikRIP.png","(clap)":"(clap).gif","(giggle)":"(giggle).gif","dan10":"dan10.png","(waiting)":"(waiting).gif","(bandit)":"(bandit).gif","eloiseSWA":"eloiseSWA.gif","(cool)":"(cool).gif","(jaw)":"(jaw).png","eloiseSleeper":"eloiseSleeper.png","eloiseRage":"eloiseRage.png","danScience":"danScience.png","dan7":"dan7.png","(doh)":"(doh).gif","lirikOHGOD":"lirikOHGOD.png","danWhodat":"danWhodat.png","danUSA":"danUSA.png","(tumbleweed)":"(tumbleweed).gif","(smirk)":"(smirk).gif","(ci)":"(ci).gif","forsenRope":"forsenRope.png","danWTF":"danWTF.png","heyouBaguette":"heyouBaguette.png","(makeup)":"(makeup).gif","(lalala)":"(lalala).gif","danSun":"danSun.png","danHmm":"danHmm.png","danOMG":"danOMG.png","(grin)":"(grin).gif","(wave)":"(wave).gif"}